{
  "$schema": "https://developer.microsoft.com/json-schemas/rush/v5/rush.schema.json",
  "rushVersion": "5.119.0",
  "pnpmVersion": "8.15.1",
  "nodeSupportedVersionRange": ">=18.0.0",
  "projectFolderMinDepth": 2,
  "projectFolderMaxDepth": 2,
  "projects": [
    {
      "packageName": "@agikit-slim/core",
      "projectFolder": "packages/core",
      "versionPolicyName": "agikit-slim-core",
      "shouldPublish": true
    },
    {
      "packageName": "@agikit-slim/cli",
      "projectFolder": "packages/cli",
      "versionPolicyName": "agikit-slim-cli",
      "shouldPublish": true
    },
    {
      "packageName": "@agikit-slim/examples",
      "projectFolder": "packages/examples",
      "shouldPublish": false
    }
  ]
}
